Workbook

Sheet Dashboard
A1: DATA INTELLIGENCE DASHBOARD
A3: TOTAL REVENUE | D3: TRANSACTIONS | G3: UNITS SOLD | J3: AVG TRANSACTION
A4: =SUM('Raw Data'!N2:N251) -> 229192.47 | D4: =COUNTA('Raw Data'!A2:A251) -> 250 | G4: =SUM('Raw Data'!H2:H251) -> 753 | J4: =AVERAGE('Raw Data'!N2:N251) -> 916.76988
J6: KEY INSIGHTS
J7: Top Customer | K7: =INDEX(Analysis!E22:E71,MATCH(MAX(Analysis!F22:F71),Analysis!F22:F71,0)) -> Mark Carter
J8: Most Sold Product | K8: =INDEX(Analysis!A22:A31,MATCH(MAX(Analysis!B22:B31),Analysis!B22:B31,0)) -> Bookshelf
J9: Top Region | K9: =INDEX(Analysis!A13:A17,MATCH(MAX(Analysis!B13:B17),Analysis!B13:B17,0)) -> East
A32: PROJECT INSIGHTS & STORYTELLING
A34: Highest Revenue Region | D34: =INDEX(Analysis!A13:A17,MATCH(MAX(Analysis!B13:B17),Analysis!B13:B17,0)) -> East
A35: Top Revenue Product | D35: =INDEX(Analysis!A22:A31,MATCH(MAX(Analysis!C22:C31),Analysis!C22:C31,0)) -> Laptop
A36: Most Frequently Purchased Product | D36: =INDEX(Analysis!A94:A103,MATCH(MAX(Analysis!C94:C103),Analysis!C94:C103,0)) -> Bookshelf
A37: Highest Value Customer | D37: =INDEX(Analysis!E22:E71,MATCH(MAX(Analysis!F22:F71),Analysis!F22:F71,0)) -> Mark Carter
A39: Storytelling Summary
A40: •The dashboard shows total sales, revenue, units sold and average transaction value.
A41: •The region and product charts help to understand which region and product perform better.
A42: • The monthly sales report shows changes in revenue over time.
A43: • The customer and product analysis helps identify regular customers and popular products.

Sheet Raw Data
A1: Transaction_ID | B1: Date | C1: Customer_ID | D1: Customer_Name | E1: Product_ID | F1: Product_Name | G1: Category | H1: Quantity | I1: Unit_Price | J1: Payment_Method | K1: Region | L1: Customer_Segment | M1: Customer_Since | N1: Total_Amount | O1: Customer Tenure (Years) | P1: Month End | Q1: Revenue Check | R1: Purchase Timestamp
A2: TRX0155 | B2: 45393 | C2: CUST023 | D2: Paul Baker | E2: P009 | F2: Monitor | G2: Electronics | H2: 3 | I2: 249.99 | J2: Cash | K2: Central | L2: Basic | M2: 44425 | N2: 749.97 | O2: =IFERROR(DATEDIF(M2,TODAY(),"Y"),0) -> 5 | P2: =EOMONTH(B2,0) -> 45412 | Q2: =IF(ABS(N2-H2*I2)<1,"OK","Check") -> OK | R2: =IF(A2<>"",NOW(),"") -> 46310.671
A3: TRX0023 | B3: 45396 | C3: CUST013 | D3: Joseph Jackson | E3: P009 | F3: Monitor | G3: Electronics | H3: 3 | I3: 249.99 | J3: Credit Card | K3: Central | L3: Premium | M3: 44575 | N3: 749.97 | O3: =IFERROR(DATEDIF(M3,TODAY(),"Y"),0) -> 4 | P3: =EOMONTH(B3,0) -> 45412 | Q3: =IF(ABS(N3-H3*I3)<1,"OK","Check") -> OK | R3: =IF(A3<>"",NOW(),"") -> 46310.671
A4: TRX0139 | B4: 45399 | C4: CUST021 | D4: Kevin Scott | E4: P005 | F4: Blender | G4: Appliances | H4: 3 | I4: 59.99 | J4: PayPal | K4: South | L4: Standard | M4: 45262 | N4: 179.97 | O4: =IFERROR(DATEDIF(M4,TODAY(),"Y"),0) -> 2 | P4: =EOMONTH(B4,0) -> 45412 | Q4: =IF(ABS(N4-H4*I4)<1,"OK","Check") -> OK | R4: =IF(A4<>"",NOW(),"") -> 46310.671
A5: TRX0043 | B5: 45400 | C5: CUST046 | D5: Kathleen Bennett | E5: P005 | F5: Blender | G5: Appliances | H5: 3 | I5: 59.99 | J5: Cash | K5: North | L5: Premium | M5: 45114 | N5: 179.97 | O5: =IFERROR(DATEDIF(M5,TODAY(),"Y"),0) -> 3 | P5: =EOMONTH(B5,0) -> 45412 | Q5: =IF(ABS(N5-H5*I5)<1,"OK","Check") -> OK | R5: =IF(A5<>"",NOW(),"") -> 46310.671
A6: TRX0212 | B6: 45400 | C6: CUST003 | D6: Michael Brown | E6: P008 | F6: Bookshelf | G6: Furniture | H6: 5 | I6: 149.99 | J6: Credit Card | K6: North | L6: Premium | M6: 45295 | N6: 749.95 | O6: =IFERROR(DATEDIF(M6,TODAY(),"Y"),0) -> 2 | P6: =EOMONTH(B6,0) -> 45412 | Q6: =IF(ABS(N6-H6*I6)<1,"OK","Check") -> OK | R6: =IF(A6<>"",NOW(),"") -> 46310.671
A7: TRX0092 | B7: 45403 | C7: CUST024 | D7: Dorothy Nelson | E7: P005 | F7: Blender | G7: Appliances | H7: 2 | I7: 59.99 | J7: Cash | K7: West | L7: Standard | M7: 44746 | N7: 119.98 | O7: =IFERROR(DATEDIF(M7,TODAY(),"Y"),0) -> 4 | P7: =EOMONTH(B7,0) -> 45412 | Q7: =IF(ABS(N7-H7*I7)<1,"OK","Check") -> OK | R7: =IF(A7<>"",NOW(),"") -> 46310.671
A8: TRX0193 | B8: 45403 | C8: CUST024 | D8: Dorothy Nelson | E8: P003 | F8: Headphones | G8: Electronics | H8: 5 | I8: 149.99 | J8: Credit Card | K8: Central | L8: Standard | M8: 44418 | N8: 749.95 | O8: =IFERROR(DATEDIF(M8,TODAY(),"Y"),0) -> 5 | P8: =EOMONTH(B8,0) -> 45412 | Q8: =IF(ABS(N8-H8*I8)<1,"OK","Check") -> OK | R8: =IF(A8<>"",NOW(),"") -> 46310.671
A9: TRX0240 | B9: 45403 | C9: CUST017 | D9: Charles Allen | E9: P005 | F9: Blender | G9: Appliances | H9: 3 | I9: 59.99 | J9: Debit Card | K9: South | L9: Basic | M9: 45007 | N9: 179.97 | O9: =IFERROR(DATEDIF(M9,TODAY(),"Y"),0) -> 3 | P9: =EOMONTH(B9,0) -> 45412 | Q9: =IF(ABS(N9-H9*I9)<1,"OK","Check") -> OK | R9: =IF(A9<>"",NOW(),"") -> 46310.671
A10: TRX0135 | B10: 45405 | C10: CUST009 | D10: Robert Thomas | E10: P001 | F10: Laptop | G10: Electronics | H10: 3 | I10: 899.99 | J10: PayPal | K10: East | L10: Standard | M10: 45299 | N10: 2699.97 | O10: =IFERROR(DATEDIF(M10,TODAY(),"Y"),0) -> 2 | P10: =EOMONTH(B10,0) -> 45412 | Q10: =IF(ABS(N10-H10*I10)<1,"OK","Check") -> OK | R10: =IF(A10<>"",NOW(),"") -> 46310.671
A11: TRX0185 | B11: 45408 | C11: CUST026 | D11: Karen Hill | E11: P005 | F11: Blender | G11: Appliances | H11: 3 | I11: 59.99 | J11: Cash | K11: West | L11: Premium | M11: 45207 | N11: 179.97 | O11: =IFERROR(DATEDIF(M11,TODAY(),"Y"),0) -> 3 | P11: =EOMONTH(B11,0) -> 45412 | Q11: =IF(ABS(N11-H11*I11)<1,"OK","Check") -> OK | R11: =IF(A11<>"",NOW(),"") -> 46310.671
A12: TRX0138 | B12: 45408 | C12: CUST022 | D12: Susan Green | E12: P008 | F12: Bookshelf | G12: Furniture | H12: 1 | I12: 149.99 | J12: Credit Card | K12: West | L12: Standard | M12: 45103 | N12: 149.99 | O12: =IFERROR(DATEDIF(M12,TODAY(),"Y"),0) -> 3 | P12: =EOMONTH(B12,0) -> 45412 | Q12: =IF(ABS(N12-H12*I12)<1,"OK","Check") -> OK | R12: =IF(A12<>"",NOW(),"") -> 46310.671
A13: TRX0209 | B13: 45408 | C13: CUST046 | D13: Kathleen Bennett | E13: P008 | F13: Bookshelf | G13: Furniture | H13: 5 | I13: 149.99 | J13: Debit Card | K13: North | L13: Basic | M13: 44830 | N13: 749.95 | O13: =IFERROR(DATEDIF(M13,TODAY(),"Y"),0) -> 4 | P13: =EOMONTH(B13,0) -> 45412 | Q13: =IF(ABS(N13-H13*I13)<1,"OK","Check") -> OK | R13: =IF(A13<>"",NOW(),"") -> 46310.671
... A251: TRX0064 | B251: 45758 | C251: CUST031 | D251: Steven Turner | E251: P010 | F251: Keyboard | G251: Electronics | H251: 3 | I251: 89.99 | J251: Debit Card | K251: North | L251: Premium | M251: 44878 | N251: 269.97 | O251: =IFERROR(DATEDIF(M251,TODAY(),"Y"),0) -> 3 | P251: =EOMONTH(B251,0) -> 45777 | Q251: =IF(ABS(N251-H251*I251)<1,"OK","Check") -> OK | R251: =IF(A251<>"",NOW(),"") -> 46310.671

Sheet Analysis
A1: DATA ANALYSIS & SUMMARY
A3: Key Metric | B3: Result | J3: PIVOT SUMMARY
A4: Total Revenue | B4: =SUM('Raw Data'!N2:N251) -> 229192.47 | J4: Region | K4: Blender | L4: Bookshelf | M4: Coffee Maker | N4: Desk | O4: Headphones | P4: Keyboard | Q4: Laptop | R4: Monitor | S4: Office Chair | T4: Smartphone | U4: Grand Total
A5: Transactions | B5: =COUNTA('Raw Data'!A2:A251) -> 250 | J5: Central | K5: =SUMIFS('Raw Data'!$N$2:$N$251,'Raw Data'!$K$2:$K$251,$J5,'Raw Data'!$F$2:$F$251,K$4) -> 959.84 | L5: =SUMIFS('Raw Data'!$N$2:$N$251,'Raw Data'!$K$2:$K$251,$J5,'Raw Data'!$F$2:$F$251,L$4) -> 4799.68 | M5: =SUMIFS('Raw Data'!$N$2:$N$251,'Raw Data'!$K$2:$K$251,$J5,'Raw Data'!$F$2:$F$251,M$4) -> 1039.87 | N5: =SUMIFS('Raw Data'!$N$2:$N$251,'Raw Data'!$K$2:$K$251,$J5,'Raw Data'!$F$2:$F$251,N$4) -> 5999.8 | O5: =SUMIFS('Raw Data'!$N$2:$N$251,'Raw Data'!$K$2:$K$251,$J5,'Raw Data'!$F$2:$F$251,O$4) -> 1199.92 | P5: =SUMIFS('Raw Data'!$N$2:$N$251,'Raw Data'!$K$2:$K$251,$J5,'Raw Data'!$F$2:$F$251,P$4) -> 1439.84 | Q5: =SUMIFS('Raw Data'!$N$2:$N$251,'Raw Data'!$K$2:$K$251,$J5,'Raw Data'!$F$2:$F$251,Q$4) -> 7199.92 | R5: =SUMIFS('Raw Data'!$N$2:$N$251,'Raw Data'!$K$2:$K$251,$J5,'Raw Data'!$F$2:$F$251,R$4) -> 5249.79 | ... T5: =SUMIFS('Raw Data'!$N$2:$N$251,'Raw Data'!$K$2:$K$251,$J5,'Raw Data'!$F$2:$F$251,T$4) -> 9799.86 | U5: =SUM(K5:T5) -> 41288.34
A6: Units Sold | B6: =SUM('Raw Data'!H2:H251) -> 753 | J6: East | K6: =SUMIFS('Raw Data'!$N$2:$N$251,'Raw Data'!$K$2:$K$251,$J6,'Raw Data'!$F$2:$F$251,K$4) -> 1199.8 | L6: =SUMIFS('Raw Data'!$N$2:$N$251,'Raw Data'!$K$2:$K$251,$J6,'Raw Data'!$F$2:$F$251,L$4) -> 1799.88 | M6: =SUMIFS('Raw Data'!$N$2:$N$251,'Raw Data'!$K$2:$K$251,$J6,'Raw Data'!$F$2:$F$251,M$4) -> 1039.87 | N6: =SUMIFS('Raw Data'!$N$2:$N$251,'Raw Data'!$K$2:$K$251,$J6,'Raw Data'!$F$2:$F$251,N$4) -> 3599.88 | O6: =SUMIFS('Raw Data'!$N$2:$N$251,'Raw Data'!$K$2:$K$251,$J6,'Raw Data'!$F$2:$F$251,O$4) -> 1949.87 | P6: =SUMIFS('Raw Data'!$N$2:$N$251,'Raw Data'!$K$2:$K$251,$J6,'Raw Data'!$F$2:$F$251,P$4) -> 1349.85 | Q6: =SUMIFS('Raw Data'!$N$2:$N$251,'Raw Data'!$K$2:$K$251,$J6,'Raw Data'!$F$2:$F$251,Q$4) -> 27899.69 | R6: =SUMIFS('Raw Data'!$N$2:$N$251,'Raw Data'!$K$2:$K$251,$J6,'Raw Data'!$F$2:$F$251,R$4) -> 4749.81 | ... T6: =SUMIFS('Raw Data'!$N$2:$N$251,'Raw Data'!$K$2:$K$251,$J6,'Raw Data'!$F$2:$F$251,T$4) -> 14699.79 | U6: =SUM(K6:T6) -> 59288.39
A7: Average Transaction | B7: =AVERAGE('Raw Data'!N2:N251) -> 916.76988 | J7: North | K7: =SUMIFS('Raw Data'!$N$2:$N$251,'Raw Data'!$K$2:$K$251,$J7,'Raw Data'!$F$2:$F$251,K$4) -> 479.92 | L7: =SUMIFS('Raw Data'!$N$2:$N$251,'Raw Data'!$K$2:$K$251,$J7,'Raw Data'!$F$2:$F$251,L$4) -> 4949.67 | M7: =SUMIFS('Raw Data'!$N$2:$N$251,'Raw Data'!$K$2:$K$251,$J7,'Raw Data'!$F$2:$F$251,M$4) -> 639.92 | N7: =SUMIFS('Raw Data'!$N$2:$N$251,'Raw Data'!$K$2:$K$251,$J7,'Raw Data'!$F$2:$F$251,N$4) -> 2099.93 | O7: =SUMIFS('Raw Data'!$N$2:$N$251,'Raw Data'!$K$2:$K$251,$J7,'Raw Data'!$F$2:$F$251,O$4) -> 1949.87 | P7: =SUMIFS('Raw Data'!$N$2:$N$251,'Raw Data'!$K$2:$K$251,$J7,'Raw Data'!$F$2:$F$251,P$4) -> 1889.79 | Q7: =SUMIFS('Raw Data'!$N$2:$N$251,'Raw Data'!$K$2:$K$251,$J7,'Raw Data'!$F$2:$F$251,Q$4) -> 12599.86 | R7: =SUMIFS('Raw Data'!$N$2:$N$251,'Raw Data'!$K$2:$K$251,$J7,'Raw Data'!$F$2:$F$251,R$4) -> 5999.76 | ... T7: =SUMIFS('Raw Data'!$N$2:$N$251,'Raw Data'!$K$2:$K$251,$J7,'Raw Data'!$F$2:$F$251,T$4) -> 16799.76 | U7: =SUM(K7:T7) -> 50808.31
A8: Unique Customers | B8: =SUMPRODUCT(('Raw Data'!D2:D251<>"")/COUNTIF('Raw Data'!D2:D251,'Raw Data'!D2:D251)) -> 50 | J8: South | K8: =SUMIFS('Raw Data'!$N$2:$N$251,'Raw Data'!$K$2:$K$251,$J8,'Raw Data'!$F$2:$F$251,K$4) -> 779.87 | L8: =SUMIFS('Raw Data'!$N$2:$N$251,'Raw Data'!$K$2:$K$251,$J8,'Raw Data'!$F$2:$F$251,L$4) -> 1349.91 | M8: =SUMIFS('Raw Data'!$N$2:$N$251,'Raw Data'!$K$2:$K$251,$J8,'Raw Data'!$F$2:$F$251,M$4) -> 319.96 | N8: =SUMIFS('Raw Data'!$N$2:$N$251,'Raw Data'!$K$2:$K$251,$J8,'Raw Data'!$F$2:$F$251,N$4) -> 6599.78 | O8: =SUMIFS('Raw Data'!$N$2:$N$251,'Raw Data'!$K$2:$K$251,$J8,'Raw Data'!$F$2:$F$251,O$4) -> 899.94 | P8: =SUMIFS('Raw Data'!$N$2:$N$251,'Raw Data'!$K$2:$K$251,$J8,'Raw Data'!$F$2:$F$251,P$4) -> 2249.75 | Q8: =SUMIFS('Raw Data'!$N$2:$N$251,'Raw Data'!$K$2:$K$251,$J8,'Raw Data'!$F$2:$F$251,Q$4) -> 12599.86 | R8: =SUMIFS('Raw Data'!$N$2:$N$251,'Raw Data'!$K$2:$K$251,$J8,'Raw Data'!$F$2:$F$251,R$4) -> 3499.86 | ... T8: =SUMIFS('Raw Data'!$N$2:$N$251,'Raw Data'!$K$2:$K$251,$J8,'Raw Data'!$F$2:$F$251,T$4) -> 6299.91 | U8: =SUM(K8:T8) -> 36398.75
J9: West | K9: =SUMIFS('Raw Data'!$N$2:$N$251,'Raw Data'!$K$2:$K$251,$J9,'Raw Data'!$F$2:$F$251,K$4) -> 1799.7 | L9: =SUMIFS('Raw Data'!$N$2:$N$251,'Raw Data'!$K$2:$K$251,$J9,'Raw Data'!$F$2:$F$251,L$4) -> 2399.84 | M9: =SUMIFS('Raw Data'!$N$2:$N$251,'Raw Data'!$K$2:$K$251,$J9,'Raw Data'!$F$2:$F$251,M$4) -> 79.99 | N9: =SUMIFS('Raw Data'!$N$2:$N$251,'Raw Data'!$K$2:$K$251,$J9,'Raw Data'!$F$2:$F$251,N$4) -> 5099.83 | O9: =SUMIFS('Raw Data'!$N$2:$N$251,'Raw Data'!$K$2:$K$251,$J9,'Raw Data'!$F$2:$F$251,O$4) -> 1049.93 | P9: =SUMIFS('Raw Data'!$N$2:$N$251,'Raw Data'!$K$2:$K$251,$J9,'Raw Data'!$F$2:$F$251,P$4) -> 1079.88 | Q9: =SUMIFS('Raw Data'!$N$2:$N$251,'Raw Data'!$K$2:$K$251,$J9,'Raw Data'!$F$2:$F$251,Q$4) -> 7199.92 | R9: =SUMIFS('Raw Data'!$N$2:$N$251,'Raw Data'!$K$2:$K$251,$J9,'Raw Data'!$F$2:$F$251,R$4) -> 2499.9 | ... T9: =SUMIFS('Raw Data'!$N$2:$N$251,'Raw Data'!$K$2:$K$251,$J9,'Raw Data'!$F$2:$F$251,T$4) -> 19599.72 | U9: =SUM(K9:T9) -> 41408.68
J10: Grand Total | K10: =SUM(K5:K9) -> 5219.13 | L10: =SUM(L5:L9) -> 15298.98 | M10: =SUM(M5:M9) -> 3119.61 | N10: =SUM(N5:N9) -> 23399.22 | O10: =SUM(O5:O9) -> 7049.53 | P10: =SUM(P5:P9) -> 8009.11 | Q10: =SUM(Q5:Q9) -> 67499.25 | R10: =SUM(R5:R9) -> 21999.12 | ... U10: =SUM(U5:U9) -> 229192.47
A11: Regional Sales | E11: Sales by Category
A12: Region | B12: Revenue | C12: Transactions | E12: Category | F12: Revenue | G12: Units
A13: Central | B13: =SUMIF('Raw Data'!K$2:K$251,A13,'Raw Data'!N$2:N$251) -> 41288.34 | C13: =COUNTIF('Raw Data'!K$2:K$251,A13) -> 54 | E13: Appliances | F13: =SUMIF('Raw Data'!G$2:G$251,E13,'Raw Data'!N$2:N$251) -> 8338.74 | G13: =SUMIF('Raw Data'!G$2:G$251,E13,'Raw Data'!H$2:H$251) -> 126
A14: East | B14: =SUMIF('Raw Data'!K$2:K$251,A14,'Raw Data'!N$2:N$251) -> 59288.39 | C14: =COUNTIF('Raw Data'!K$2:K$251,A14) -> 48 | E14: Electronics | F14: =SUMIF('Raw Data'!G$2:G$251,E14,'Raw Data'!N$2:N$251) -> 171756.05 | G14: =SUMIF('Raw Data'!G$2:G$251,E14,'Raw Data'!H$2:H$251) -> 395 | J14: REGRESSION SUMMARY
A15: North | B15: =SUMIF('Raw Data'!K$2:K$251,A15,'Raw Data'!N$2:N$251) -> 50808.31 | C15: =COUNTIF('Raw Data'!K$2:K$251,A15) -> 59 | E15: Furniture | F15: =SUMIF('Raw Data'!G$2:G$251,E15,'Raw Data'!N$2:N$251) -> 49097.68 | G15: =SUMIF('Raw Data'!G$2:G$251,E15,'Raw Data'!H$2:H$251) -> 232 | J15: Observation | K15: 250
A16: South | B16: =SUMIF('Raw Data'!K$2:K$251,A16,'Raw Data'!N$2:N$251) -> 36398.75 | C16: =COUNTIF('Raw Data'!K$2:K$251,A16) -> 42 | J16: Y Variable | K16: Total_Amount
A17: West | B17: =SUMIF('Raw Data'!K$2:K$251,A17,'Raw Data'!N$2:N$251) -> 41408.68 | C17: =COUNTIF('Raw Data'!K$2:K$251,A17) -> 47 | J17: X Variable | K17: Quantity
J18: Regression Slope | K18: 353.793
J19: Intercept | K19: -148.85465
A20: Product Performance | E20: Top Customers | J20: R Square | K20: 0.20983762
A21: Product | B21: Units Sold | C21: Revenue | E21: Customer | F21: Revenue | G21: Transactions | J21: Correlation | K21: 0.45808036
A22: Blender | B22: =SUMIF('Raw Data'!F$2:F$251,A22,'Raw Data'!H$2:H$251) -> 87 | C22: =SUMIF('Raw Data'!F$2:F$251,A22,'Raw Data'!N$2:N$251) -> 5219.13 | E22: Arthur Edwards | F22: =SUMIF('Raw Data'!D$2:D$251,E22,'Raw Data'!N$2:N$251) -> 1559.94 | G22: =COUNTIF('Raw Data'!D$2:D$251,E22) -> 3
A23: Bookshelf | B23: =SUMIF('Raw Data'!F$2:F$251,A23,'Raw Data'!H$2:H$251) -> 102 | C23: =SUMIF('Raw Data'!F$2:F$251,A23,'Raw Data'!N$2:N$251) -> 15298.98 | E23: Barbara Young | F23: =SUMIF('Raw Data'!D$2:D$251,E23,'Raw Data'!N$2:N$251) -> 10649.8 | G23: =COUNTIF('Raw Data'!D$2:D$251,E23) -> 5
A24: Coffee Maker | B24: =SUMIF('Raw Data'!F$2:F$251,A24,'Raw Data'!H$2:H$251) -> 39 | C24: =SUMIF('Raw Data'!F$2:F$251,A24,'Raw Data'!N$2:N$251) -> 3119.61 | E24: Betty Campbell | F24: =SUMIF('Raw Data'!D$2:D$251,E24,'Raw Data'!N$2:N$251) -> 5649.84 | G24: =COUNTIF('Raw Data'!D$2:D$251,E24) -> 5
A25: Desk | B25: =SUMIF('Raw Data'!F$2:F$251,A25,'Raw Data'!H$2:H$251) -> 78 | C25: =SUMIF('Raw Data'!F$2:F$251,A25,'Raw Data'!N$2:N$251) -> 23399.22 | E25: Carol Evans | F25: =SUMIF('Raw Data'!D$2:D$251,E25,'Raw Data'!N$2:N$251) -> 1149.93 | G25: =COUNTIF('Raw Data'!D$2:D$251,E25) -> 3
A26: Headphones | B26: =SUMIF('Raw Data'!F$2:F$251,A26,'Raw Data'!H$2:H$251) -> 47 | C26: =SUMIF('Raw Data'!F$2:F$251,A26,'Raw Data'!N$2:N$251) -> 7049.53 | E26: Charles Allen | F26: =SUMIF('Raw Data'!D$2:D$251,E26,'Raw Data'!N$2:N$251) -> 5089.73 | G26: =COUNTIF('Raw Data'!D$2:D$251,E26) -> 9
A27: Keyboard | B27: =SUMIF('Raw Data'!F$2:F$251,A27,'Raw Data'!H$2:H$251) -> 89 | C27: =SUMIF('Raw Data'!F$2:F$251,A27,'Raw Data'!N$2:N$251) -> 8009.11 | E27: Cynthia Price | F27: =SUMIF('Raw Data'!D$2:D$251,E27,'Raw Data'!N$2:N$251) -> 3769.83 | G27: =COUNTIF('Raw Data'!D$2:D$251,E27) -> 5
A28: Laptop | B28: =SUMIF('Raw Data'!F$2:F$251,A28,'Raw Data'!H$2:H$251) -> 75 | C28: =SUMIF('Raw Data'!F$2:F$251,A28,'Raw Data'!N$2:N$251) -> 67499.25 | E28: Daniel King | F28: =SUMIF('Raw Data'!D$2:D$251,E28,'Raw Data'!N$2:N$251) -> 7309.8 | G28: =COUNTIF('Raw Data'!D$2:D$251,E28) -> 7
A29: Monitor | B29: =SUMIF('Raw Data'!F$2:F$251,A29,'Raw Data'!H$2:H$251) -> 88 | C29: =SUMIF('Raw Data'!F$2:F$251,A29,'Raw Data'!N$2:N$251) -> 21999.12 | E29: David Martinez | F29: =SUMIF('Raw Data'!D$2:D$251,E29,'Raw Data'!N$2:N$251) -> 1809.84 | G29: =COUNTIF('Raw Data'!D$2:D$251,E29) -> 6
A30: Office Chair | B30: =SUMIF('Raw Data'!F$2:F$251,A30,'Raw Data'!H$2:H$251) -> 52 | C30: =SUMIF('Raw Data'!F$2:F$251,A30,'Raw Data'!N$2:N$251) -> 10399.48 | E30: Dennis Gray | F30: =SUMIF('Raw Data'!D$2:D$251,E30,'Raw Data'!N$2:N$251) -> 479.92 | G30: =COUNTIF('Raw Data'!D$2:D$251,E30) -> 2
A31: Smartphone | B31: =SUMIF('Raw Data'!F$2:F$251,A31,'Raw Data'!H$2:H$251) -> 96 | C31: =SUMIF('Raw Data'!F$2:F$251,A31,'Raw Data'!N$2:N$251) -> 67199.04 | E31: Dorothy Nelson | F31: =SUMIF('Raw Data'!D$2:D$251,E31,'Raw Data'!N$2:N$251) -> 8269.79 | G31: =COUNTIF('Raw Data'!D$2:D$251,E31) -> 6
E32: Douglas Watson | F32: =SUMIF('Raw Data'!D$2:D$251,E32,'Raw Data'!N$2:N$251) -> 4829.89 | G32: =COUNTIF('Raw Data'!D$2:D$251,E32) -> 4
E33: Edward Mitchell | F33: =SUMIF('Raw Data'!D$2:D$251,E33,'Raw Data'!N$2:N$251) -> 11919.77 | G33: =COUNTIF('Raw Data'!D$2:D$251,E33) -> 6
E34: Elizabeth Hall | F34: =SUMIF('Raw Data'!D$2:D$251,E34,'Raw Data'!N$2:N$251) -> 3649.86 | G34: =COUNTIF('Raw Data'!D$2:D$251,E34) -> 4
E35: Emma Wilson | F35: =SUMIF('Raw Data'!D$2:D$251,E35,'Raw Data'!N$2:N$251) -> 1229.88 | G35: =COUNTIF('Raw Data'!D$2:D$251,E35) -> 5
E36: Frank Torres | F36: =SUMIF('Raw Data'!D$2:D$251,E36,'Raw Data'!N$2:N$251) -> 1479.91 | G36: =COUNTIF('Raw Data'!D$2:D$251,E36) -> 5
E37: George Adams | F37: =SUMIF('Raw Data'!D$2:D$251,E37,'Raw Data'!N$2:N$251) -> 3779.93 | G37: =COUNTIF('Raw Data'!D$2:D$251,E37) -> 3
E38: Gerald Murphy | F38: =SUMIF('Raw Data'!D$2:D$251,E38,'Raw Data'!N$2:N$251) -> 6379.87 | G38: =COUNTIF('Raw Data'!D$2:D$251,E38) -> 4
E39: Harry Morgan | F39: =SUMIF('Raw Data'!D$2:D$251,E39,'Raw Data'!N$2:N$251) -> 5519.89 | G39: =COUNTIF('Raw Data'!D$2:D$251,E39) -> 4
E40: Helen Roberts | F40: =SUMIF('Raw Data'!D$2:D$251,E40,'Raw Data'!N$2:N$251) -> 6459.79 | G40: =COUNTIF('Raw Data'!D$2:D$251,E40) -> 7
E41: James Johnson | F41: =SUMIF('Raw Data'!D$2:D$251,E41,'Raw Data'!N$2:N$251) -> 179.97 | G41: =COUNTIF('Raw Data'!D$2:D$251,E41) -> 1
E42: Jennifer Taylor | F42: =SUMIF('Raw Data'!D$2:D$251,E42,'Raw Data'!N$2:N$251) -> 4739.85 | G42: =COUNTIF('Raw Data'!D$2:D$251,E42) -> 4
E43: John Smith | F43: =SUMIF('Raw Data'!D$2:D$251,E43,'Raw Data'!N$2:N$251) -> 599.96 | G43: =COUNTIF('Raw Data'!D$2:D$251,E43) -> 1
... E71: William White | F71: =SUMIF('Raw Data'!D$2:D$251,E71,'Raw Data'!N$2:N$251) -> 4749.91 | G71: =COUNTIF('Raw Data'!D$2:D$251,E71) -> 3
A73: SCENARIO MANAGER & GOAL SEEK
A75: Base Revenue | B75: =SUM('Raw Data'!N2:N251) -> 229192.47
A76: Base Units Sold | B76: =SUM('Raw Data'!H2:H251) -> 753
A78: Scenario Comparison (discount impact)
A79: Scenario | B79: Discount Rate | C79: Estimated Net Revenue | D79: Difference vs Base
A80: Best Case | B80: 0 | C80: =$B$75*(1-B80) -> 229192.47 | D80: =C80-$B$75 -> 0
A81: Normal Case | B81: 0.05 | C81: =$B$75*(1-B81) -> 217732.85 | D81: =C81-$B$75 -> -11459.624
A82: Worst Case | B82: 0.1 | C82: =$B$75*(1-B82) -> 206273.22 | D82: =C82-$B$75 -> -22919.247
A84: Goal Seek Model
A85: Discount Rate (input) | B85: 0.05
A86: Calculated Net Revenue | B86: =$B$75*(1-$B$85) -> 217732.85
A87: Target Net Revenue (input) | B87: =$B$75*0.9 -> 206273.22
A88: Difference (Calculated - Target) | B88: =B86-B87 -> 11459.624
A92: PRODUCT FREQUENCY & REPEATING CUSTOMER NAMES
A93: Product | B93: Units Sold | C93: Purchase Count | D93: Customer Name | E93: Name Repeats | F93: Transactions
A94: Blender | B94: =SUMIF('Raw Data'!$F$2:$F$251,A94,'Raw Data'!$H$2:$H$251) -> 87 | C94: =COUNTIF('Raw Data'!$F$2:$F$251,A94) -> 29 | D94: Arthur Edwards | E94: =IF(F94>1,"Repeating","Unique") -> Repeating | F94: =COUNTIF('Raw Data'!$D$2:$D$251,D94) -> 3
A95: Bookshelf | B95: =SUMIF('Raw Data'!$F$2:$F$251,A95,'Raw Data'!$H$2:$H$251) -> 102 | C95: =COUNTIF('Raw Data'!$F$2:$F$251,A95) -> 35 | D95: Barbara Young | E95: =IF(F95>1,"Repeating","Unique") -> Repeating | F95: =COUNTIF('Raw Data'!$D$2:$D$251,D95) -> 5
A96: Coffee Maker | B96: =SUMIF('Raw Data'!$F$2:$F$251,A96,'Raw Data'!$H$2:$H$251) -> 39 | C96: =COUNTIF('Raw Data'!$F$2:$F$251,A96) -> 14 | D96: Betty Campbell | E96: =IF(F96>1,"Repeating","Unique") -> Repeating | F96: =COUNTIF('Raw Data'!$D$2:$D$251,D96) -> 5
A97: Desk | B97: =SUMIF('Raw Data'!$F$2:$F$251,A97,'Raw Data'!$H$2:$H$251) -> 78 | C97: =COUNTIF('Raw Data'!$F$2:$F$251,A97) -> 26 | D97: Carol Evans | E97: =IF(F97>1,"Repeating","Unique") -> Repeating | F97: =COUNTIF('Raw Data'!$D$2:$D$251,D97) -> 3
A98: Headphones | B98: =SUMIF('Raw Data'!$F$2:$F$251,A98,'Raw Data'!$H$2:$H$251) -> 47 | C98: =COUNTIF('Raw Data'!$F$2:$F$251,A98) -> 16 | D98: Charles Allen | E98: =IF(F98>1,"Repeating","Unique") -> Repeating | F98: =COUNTIF('Raw Data'!$D$2:$D$251,D98) -> 9
A99: Keyboard | B99: =SUMIF('Raw Data'!$F$2:$F$251,A99,'Raw Data'!$H$2:$H$251) -> 89 | C99: =COUNTIF('Raw Data'!$F$2:$F$251,A99) -> 34 | D99: Cynthia Price | E99: =IF(F99>1,"Repeating","Unique") -> Repeating | F99: =COUNTIF('Raw Data'!$D$2:$D$251,D99) -> 5
A100: Laptop | B100: =SUMIF('Raw Data'!$F$2:$F$251,A100,'Raw Data'!$H$2:$H$251) -> 75 | C100: =COUNTIF('Raw Data'!$F$2:$F$251,A100) -> 24 | D100: Daniel King | E100: =IF(F100>1,"Repeating","Unique") -> Repeating | F100: =COUNTIF('Raw Data'!$D$2:$D$251,D100) -> 7
A101: Monitor | B101: =SUMIF('Raw Data'!$F$2:$F$251,A101,'Raw Data'!$H$2:$H$251) -> 88 | C101: =COUNTIF('Raw Data'!$F$2:$F$251,A101) -> 26 | D101: David Martinez | E101: =IF(F101>1,"Repeating","Unique") -> Repeating | F101: =COUNTIF('Raw Data'!$D$2:$D$251,D101) -> 6
A102: Office Chair | B102: =SUMIF('Raw Data'!$F$2:$F$251,A102,'Raw Data'!$H$2:$H$251) -> 52 | C102: =COUNTIF('Raw Data'!$F$2:$F$251,A102) -> 15 | D102: Dennis Gray | E102: =IF(F102>1,"Repeating","Unique") -> Repeating | F102: =COUNTIF('Raw Data'!$D$2:$D$251,D102) -> 2
A103: Smartphone | B103: =SUMIF('Raw Data'!$F$2:$F$251,A103,'Raw Data'!$H$2:$H$251) -> 96 | C103: =COUNTIF('Raw Data'!$F$2:$F$251,A103) -> 31 | D103: Dorothy Nelson | E103: =IF(F103>1,"Repeating","Unique") -> Repeating | F103: =COUNTIF('Raw Data'!$D$2:$D$251,D103) -> 6
D104: Douglas Watson | E104: =IF(F104>1,"Repeating","Unique") -> Repeating | F104: =COUNTIF('Raw Data'!$D$2:$D$251,D104) -> 4
D105: Edward Mitchell | E105: =IF(F105>1,"Repeating","Unique") -> Repeating | F105: =COUNTIF('Raw Data'!$D$2:$D$251,D105) -> 6
D106: Elizabeth Hall | E106: =IF(F106>1,"Repeating","Unique") -> Repeating | F106: =COUNTIF('Raw Data'!$D$2:$D$251,D106) -> 4
D107: Emma Wilson | E107: =IF(F107>1,"Repeating","Unique") -> Repeating | F107: =COUNTIF('Raw Data'!$D$2:$D$251,D107) -> 5
D108: Frank Torres | E108: =IF(F108>1,"Repeating","Unique") -> Repeating | F108: =COUNTIF('Raw Data'!$D$2:$D$251,D108) -> 5
D109: George Adams | E109: =IF(F109>1,"Repeating","Unique") -> Repeating | F109: =COUNTIF('Raw Data'!$D$2:$D$251,D109) -> 3
D110: Gerald Murphy | E110: =IF(F110>1,"Repeating","Unique") -> Repeating | F110: =COUNTIF('Raw Data'!$D$2:$D$251,D110) -> 4
D111: Harry Morgan | E111: =IF(F111>1,"Repeating","Unique") -> Repeating | F111: =COUNTIF('Raw Data'!$D$2:$D$251,D111) -> 4
D112: Helen Roberts | E112: =IF(F112>1,"Repeating","Unique") -> Repeating | F112: =COUNTIF('Raw Data'!$D$2:$D$251,D112) -> 7
D113: James Johnson | E113: =IF(F113>1,"Repeating","Unique") -> Unique | F113: =COUNTIF('Raw Data'!$D$2:$D$251,D113) -> 1
D114: Jennifer Taylor | E114: =IF(F114>1,"Repeating","Unique") -> Repeating | F114: =COUNTIF('Raw Data'!$D$2:$D$251,D114) -> 4
D115: John Smith | E115: =IF(F115>1,"Repeating","Unique") -> Unique | F115: =COUNTIF('Raw Data'!$D$2:$D$251,D115) -> 1
... D143: William White | E143: =IF(F143>1,"Repeating","Unique") -> Repeating | F143: =COUNTIF('Raw Data'!$D$2:$D$251,D143) -> 3
A147: COMPARE TWO LISTS — MATCHING NAMES
A148: List A (first 50 transactions) | B148: List B (transactions 101–150) | C148: Matching Name | D148: Match Status
A149: ='Raw Data'!D2 -> Paul Baker | B149: ='Raw Data'!D102 -> Sandra Phillips | C149: =IF(COUNTIF($B$149:$B$198,A149)>0,A149,"") -> Paul Baker | D149: =IF(C149<>"","Match","No Match") -> Match
A150: ='Raw Data'!D3 -> Joseph Jackson | B150: ='Raw Data'!D103 -> Carol Evans | C150: =IF(COUNTIF($B$149:$B$198,A150)>0,A150,"") | D150: =IF(C150<>"","Match","No Match") -> No Match
A151: ='Raw Data'!D4 -> Kevin Scott | B151: ='Raw Data'!D104 -> Paul Baker | C151: =IF(COUNTIF($B$149:$B$198,A151)>0,A151,"") | D151: =IF(C151<>"","Match","No Match") -> No Match
A152: ='Raw Data'!D5 -> Kathleen Bennett | B152: ='Raw Data'!D105 -> Lawrence Reed | C152: =IF(COUNTIF($B$149:$B$198,A152)>0,A152,"") -> Kathleen Bennett | D152: =IF(C152<>"","Match","No Match") -> Match
A153: ='Raw Data'!D6 -> Michael Brown | B153: ='Raw Data'!D106 -> Steven Turner | C153: =IF(COUNTIF($B$149:$B$198,A153)>0,A153,"") -> Michael Brown | D153: =IF(C153<>"","Match","No Match") -> Match
A154: ='Raw Data'!D7 -> Dorothy Nelson | B154: ='Raw Data'!D107 -> Emma Wilson | C154: =IF(COUNTIF($B$149:$B$198,A154)>0,A154,"") -> Dorothy Nelson | D154: =IF(C154<>"","Match","No Match") -> Match
A155: ='Raw Data'!D8 -> Dorothy Nelson | B155: ='Raw Data'!D108 -> Jennifer Taylor | C155: =IF(COUNTIF($B$149:$B$198,A155)>0,A155,"") -> Dorothy Nelson | D155: =IF(C155<>"","Match","No Match") -> Match
A156: ='Raw Data'!D9 -> Charles Allen | B156: ='Raw Data'!D109 -> Charles Allen | C156: =IF(COUNTIF($B$149:$B$198,A156)>0,A156,"") -> Charles Allen | D156: =IF(C156<>"","Match","No Match") -> Match
A157: ='Raw Data'!D10 -> Robert Thomas | B157: ='Raw Data'!D110 -> Dorothy Nelson | C157: =IF(COUNTIF($B$149:$B$198,A157)>0,A157,"") | D157: =IF(C157<>"","Match","No Match") -> No Match
A158: ='Raw Data'!D11 -> Karen Hill | B158: ='Raw Data'!D111 -> Kathleen Bennett | C158: =IF(COUNTIF($B$149:$B$198,A158)>0,A158,"") -> Karen Hill | D158: =IF(C158<>"","Match","No Match") -> Match
A159: ='Raw Data'!D12 -> Susan Green | B159: ='Raw Data'!D112 -> Ruth Brooks | C159: =IF(COUNTIF($B$149:$B$198,A159)>0,A159,"") | D159: =IF(C159<>"","Match","No Match") -> No Match
A160: ='Raw Data'!D13 -> Kathleen Bennett | B160: ='Raw Data'!D113 -> Karen Hill | C160: =IF(COUNTIF($B$149:$B$198,A160)>0,A160,"") -> Kathleen Bennett | D160: =IF(C160<>"","Match","No Match") -> Match
... A198: ='Raw Data'!D51 -> Paul Baker | B198: ='Raw Data'!D151 -> Frank Torres | C198: =IF(COUNTIF($B$149:$B$198,A198)>0,A198,"") -> Paul Baker | D198: =IF(C198<>"","Match","No Match") -> Match
A201: TEXT FUNCTIONS
A202: Customer Name | B202: First Name | C202: Last Name | D202: Initials / Abbreviation
A203: Arthur Edwards | B203: =LEFT(A203,FIND(" ",A203&" ")-1) -> Arthur | C203: =TRIM(MID(A203,FIND(" ",A203&" ")+1,99)) -> Edwards | D203: =UPPER(LEFT(B203,1)&LEFT(C203,1)) -> AE
A204: Barbara Young | B204: =LEFT(A204,FIND(" ",A204&" ")-1) -> Barbara | C204: =TRIM(MID(A204,FIND(" ",A204&" ")+1,99)) -> Young | D204: =UPPER(LEFT(B204,1)&LEFT(C204,1)) -> BY
...

Sheet Visualizations
A1: VISUALIZATION DATA
A3: Month | B3: Revenue | D3: Category | E3: Revenue | G3: Product | H3: Units Sold
A4: 45383 | B4: =SUMIFS('Raw Data'!$N$2:$N$251,'Raw Data'!$B$2:$B$251,">="&A4,'Raw Data'!$B$2:$B$251,"<"&EOMONTH(A4,0)+1) -> 20919.33 | D4: Appliances | E4: =SUMIF('Raw Data'!$G$2:$G$251,D4,'Raw Data'!$N$2:$N$251) -> 8338.74 | G4: Blender | H4: =SUMIF('Raw Data'!$F$2:$F$251,G4,'Raw Data'!$H$2:$H$251) -> 87
A5: 45413 | B5: =SUMIFS('Raw Data'!$N$2:$N$251,'Raw Data'!$B$2:$B$251,">="&A5,'Raw Data'!$B$2:$B$251,"<"&EOMONTH(A5,0)+1) -> 17039.35 | D5: Electronics | E5: =SUMIF('Raw Data'!$G$2:$G$251,D5,'Raw Data'!$N$2:$N$251) -> 171756.05 | G5: Bookshelf | H5: =SUMIF('Raw Data'!$F$2:$F$251,G5,'Raw Data'!$H$2:$H$251) -> 102
A6: 45444 | B6: =SUMIFS('Raw Data'!$N$2:$N$251,'Raw Data'!$B$2:$B$251,">="&A6,'Raw Data'!$B$2:$B$251,"<"&EOMONTH(A6,0)+1) -> 19299.45 | D6: Furniture | E6: =SUMIF('Raw Data'!$G$2:$G$251,D6,'Raw Data'!$N$2:$N$251) -> 49097.68 | G6: Coffee Maker | H6: =SUMIF('Raw Data'!$F$2:$F$251,G6,'Raw Data'!$H$2:$H$251) -> 39
A7: 45474 | B7: =SUMIFS('Raw Data'!$N$2:$N$251,'Raw Data'!$B$2:$B$251,">="&A7,'Raw Data'!$B$2:$B$251,"<"&EOMONTH(A7,0)+1) -> 18479.4 | G7: Desk | H7: =SUMIF('Raw Data'!$F$2:$F$251,G7,'Raw Data'!$H$2:$H$251) -> 78
A8: 45505 | B8: =SUMIFS('Raw Data'!$N$2:$N$251,'Raw Data'!$B$2:$B$251,">="&A8,'Raw Data'!$B$2:$B$251,"<"&EOMONTH(A8,0)+1) -> 15759.43 | G8: Headphones | H8: =SUMIF('Raw Data'!$F$2:$F$251,G8,'Raw Data'!$H$2:$H$251) -> 47
A9: 45536 | B9: =SUMIFS('Raw Data'!$N$2:$N$251,'Raw Data'!$B$2:$B$251,">="&A9,'Raw Data'!$B$2:$B$251,"<"&EOMONTH(A9,0)+1) -> 12989.51 | G9: Keyboard | H9: =SUMIF('Raw Data'!$F$2:$F$251,G9,'Raw Data'!$H$2:$H$251) -> 89
A10: 45566 | B10: =SUMIFS('Raw Data'!$N$2:$N$251,'Raw Data'!$B$2:$B$251,">="&A10,'Raw Data'!$B$2:$B$251,"<"&EOMONTH(A10,0)+1) -> 20609.52 | G10: Laptop | H10: =SUMIF('Raw Data'!$F$2:$F$251,G10,'Raw Data'!$H$2:$H$251) -> 75
A11: 45597 | B11: =SUMIFS('Raw Data'!$N$2:$N$251,'Raw Data'!$B$2:$B$251,">="&A11,'Raw Data'!$B$2:$B$251,"<"&EOMONTH(A11,0)+1) -> 12309.44 | G11: Monitor | H11: =SUMIF('Raw Data'!$F$2:$F$251,G11,'Raw Data'!$H$2:$H$251) -> 88
A12: 45627 | B12: =SUMIFS('Raw Data'!$N$2:$N$251,'Raw Data'!$B$2:$B$251,">="&A12,'Raw Data'!$B$2:$B$251,"<"&EOMONTH(A12,0)+1) -> 23039.3 | G12: Office Chair | H12: =SUMIF('Raw Data'!$F$2:$F$251,G12,'Raw Data'!$H$2:$H$251) -> 52
A13: 45658 | B13: =SUMIFS('Raw Data'!$N$2:$N$251,'Raw Data'!$B$2:$B$251,">="&A13,'Raw Data'!$B$2:$B$251,"<"&EOMONTH(A13,0)+1) -> 25799.15 | G13: Smartphone | H13: =SUMIF('Raw Data'!$F$2:$F$251,G13,'Raw Data'!$H$2:$H$251) -> 96
A14: 45689 | B14: =SUMIFS('Raw Data'!$N$2:$N$251,'Raw Data'!$B$2:$B$251,">="&A14,'Raw Data'!$B$2:$B$251,"<"&EOMONTH(A14,0)+1) -> 16069.38
A15: 45717 | B15: =SUMIFS('Raw Data'!$N$2:$N$251,'Raw Data'!$B$2:$B$251,">="&A15,'Raw Data'!$B$2:$B$251,"<"&EOMONTH(A15,0)+1) -> 19899.38
A16: 45748 | B16: =SUMIFS('Raw Data'!$N$2:$N$251,'Raw Data'!$B$2:$B$251,">="&A16,'Raw Data'!$B$2:$B$251,"<"&EOMONTH(A16,0)+1) -> 6979.83
